evalys/__init__.py
evalys/evalys.py
evalys/jobset.py
evalys/metrics.py
evalys/mstates.py
evalys/pstates.py
evalys/utils.py
evalys/workload.py
evalys/visu/__init__.py
evalys/visu/core.py
evalys/visu/details.py
evalys/visu/gantt.py
evalys/visu/legacy.py
evalys/visu/lifecycle.py
evalys/visu/series.py
tests/__init__.py
tests/batsim_out_jobs.csv
tests/easy_mediumWL_smallPF.csv
tests/easy_mediumWL_smallPF.swf
tests/filler_mediumWL_smallPF.csv
tests/filler_mediumWL_smallPF.swf
tests/oar_out_jobs.csv
tests/test_evalys.py
tests/test_frag_begin.csv
tests/test_frag_end.csv
tests/test_frag_high.csv
tests/test_frag_lower.csv
tests/test_frag_small_gaps.csv
tests/test_frag_very_high.csv
evalys-4.0.7.dist-info/AUTHORS.rst
evalys-4.0.7.dist-info/LICENSE
evalys-4.0.7.dist-info/METADATA
evalys-4.0.7.dist-info/WHEEL
evalys-4.0.7.dist-info/entry_points.txt
evalys-4.0.7.dist-info/top_level.txt
evalys-4.0.7.dist-info/RECORD
