Metadata-Version: 2.1
Name: evalys
Version: 4.0.7
Summary: Infrastructure Performance Evaluation Toolkit
Home-page: https://github.com/oar-team/evalys
Author: Olivier Richard
Author-email: olivier.richard@imag.fr
License: BSD
Keywords: evalys
Classifier: Development Status :: 4 - Beta
Classifier: License :: OSI Approved :: BSD License
Classifier: Programming Language :: Python
Classifier: Programming Language :: Python :: 3
Classifier: Topic :: System :: Clustering
License-File: LICENSE
License-File: AUTHORS.rst
Requires-Dist: pandas >=0.19
Requires-Dist: matplotlib <4,>=3.6.0
Requires-Dist: seaborn >=0.7
Requires-Dist: procset >=0.1.dev1
